{
    "eyebeingrecognized": "gaussianblur_gaussian_001_2_1.jpg",
    "groundtruth": "001_2_1.jpg",
    "groundtruth_eyename": "1eye_001",
    "side": "right",
    "best_match_string": "./enrolledimages/1/right/1",
    "main_keypoints": {
        "right-side": 21,
        "left-side": 19,
        "bottom": 28,
        "complete": 73
    },
    "matches": {
        "right-side": 0,
        "left-side": 0,
        "bottom": 3,
        "complete": 0
    },
    "best_match_value": 0.026785714285714284
}