{
    "eyebeingrecognized": "LucyRichardson_MedianBlur_109_2_1.jpg",
    "groundtruth": "109_2_1.jpg",
    "groundtruth_eyename": "1eye_109",
    "side": "right",
    "best_match_string": "./enrolledimages/12/right/1",
    "main_keypoints": {
        "right-side": 13,
        "left-side": 16,
        "bottom": 10,
        "complete": 41
    },
    "matches": {
        "right-side": 5,
        "left-side": 2,
        "bottom": 1,
        "complete": 5
    },
    "best_match_value": 0.18289165103189492
}