{
    "eyebeingrecognized": "LucyRichardson_bilateral_speckle_113_2_2.jpg",
    "groundtruth": "113_2_1.jpg",
    "groundtruth_eyename": "1eye_113",
    "side": "right",
    "best_match_string": "./enrolledimages/17/right/1",
    "main_keypoints": {
        "right-side": 10,
        "left-side": 13,
        "bottom": 12,
        "complete": 33
    },
    "matches": {
        "right-side": 0,
        "left-side": 1,
        "bottom": 0,
        "complete": 1
    },
    "best_match_value": 0.026806526806526808
}