{
    "eyebeingrecognized": "LucyRichardson_bilateral_poisson_003_2_2.jpg",
    "groundtruth": "003_2_1.jpg",
    "groundtruth_eyename": "1eye_003",
    "side": "right",
    "best_match_string": "./enrolledimages/132/right/1",
    "main_keypoints": {
        "right-side": 79,
        "left-side": 68,
        "bottom": 49,
        "complete": 205
    },
    "matches": {
        "right-side": 9,
        "left-side": 5,
        "bottom": 4,
        "complete": 9
    },
    "best_match_value": 0.078247138620808
}