{
    "eyebeingrecognized": "median_gaussian_003_2_1.jpg",
    "groundtruth": "003_2_1.jpg",
    "groundtruth_eyename": "1eye_003",
    "side": "right",
    "best_match_string": "./enrolledimages/132/right/1",
    "main_keypoints": {
        "right-side": 52,
        "left-side": 47,
        "bottom": 64,
        "complete": 167
    },
    "matches": {
        "right-side": 9,
        "left-side": 11,
        "bottom": 7,
        "complete": 19
    },
    "best_match_value": 0.15756673283955822
}