{
    "eyebeingrecognized": "Noisy_Speckle_casia_004_1_1.jpg",
    "groundtruth": "004_1_1.jpg",
    "groundtruth_eyename": "1eye_004",
    "side": "left",
    "best_match_string": "./enrolledimages/143/left/1",
    "main_keypoints": {
        "right-side": 79,
        "left-side": 73,
        "bottom": 92,
        "complete": 252
    },
    "matches": {
        "right-side": 35,
        "left-side": 26,
        "bottom": 29,
        "complete": 94
    },
    "best_match_value": 0.37185890564135227
}